gs/__init__.py
gs/cli.py
gs/relay.py
fleet_gs_repl-0.0.2.dist-info/METADATA
fleet_gs_repl-0.0.2.dist-info/WHEEL
fleet_gs_repl-0.0.2.dist-info/entry_points.txt
fleet_gs_repl-0.0.2.dist-info/top_level.txt
fleet_gs_repl-0.0.2.dist-info/RECORD
